<specsKey="link">http://www.flipkart.com/nikon-s3000/p/itmcuts2pjuqktas?pid=CAMCUTTFHSTGVFJH&otracker=from-search&srno=t_242&query=nikon&al=WoEJrNIH%2Ff1AsqUcEGDzEGtYAGLqsY1qr2oP8FSsnDrQSxUX9kMohYaLq2lx4bRfFLwHQxVDMNU%3D&ref=77476514-6655-436f-9c8a-f4423dfc7d42</specsKey>
<specsKey="avg_rating">4</specsKey>
<specsKey="number_of_ratings">1</specsKey>
<specsKey="number_of_reviews"></specsKey>
<specsKey="img_url">http://img6a.flixcart.com/image/camera/f/j/h/nikon-s3000-point-shoot-400x400-imacxhqyv3mqm4nc.jpeg</specsKey>
<specsKey="price">7394</specsKey>
<specsKey="title">Nikon S3000</specsKey>
<specsKey="sentiment_score">0</specsKey>
<specsKey="color">Blue</specsKey>
<specsKey="Brand">Nikon</specsKey>
<specsKey="Model ID">S3000</specsKey>
