<specsKey="link">http://www.flipkart.com/nikon-p310/p/itmd72tn6fjhyhkf?pid=CAMD7S88RH7UKMTR&otracker=from-search&srno=t_270&query=nikon&al=WoEJrNIH%2Ff188b7QQtLTZ%2BWZZXO6FeIRQrUYl%2BvTYL3nGkxu9FQsNIaLq2lx4bRfFLwHQxVDMNU%3D&ref=8531cd2f-10cf-4074-a34b-6793a7ed5459</specsKey>
<specsKey="avg_rating">4.8</specsKey>
<specsKey="number_of_ratings">6</specsKey>
<specsKey="number_of_reviews"></specsKey>
<specsKey="img_url">http://img5a.flixcart.com/image/camera/m/t/r/nikon-p310-400x400-imad8yyzyg2pc9ca.jpeg</specsKey>
<specsKey="price">13999</specsKey>
<specsKey="title">Nikon P310</specsKey>
<specsKey="sentiment_score">0</specsKey>
<specsKey="color">White</specsKey>
<specsKey="Brand">Nikon</specsKey>
<specsKey="Model ID">P310</specsKey>
